splut/__init__.py
splut/actor/__init__.py
splut/actor/future.py
splut/actor/mailbox.py
splut/actor/message.py
splut/bg/__init__.py
splut/bg/delay.py
splut-26.dist-info/METADATA
splut-26.dist-info/WHEEL
splut-26.dist-info/top_level.txt
splut-26.dist-info/RECORD
