Metadata-Version: 2.2
Name: splut
Version: 26
Summary: Actor model for Python
Home-page: https://pypi.org/project/splut/
Author: foyono
Author-email: shrovis@foyono.com
Requires-Dist: foyndation>=15
Dynamic: author
Dynamic: author-email
Dynamic: description
Dynamic: description-content-type
Dynamic: home-page
Dynamic: requires-dist
Dynamic: summary
